{
  "animateLoading": true,
  "borderRadius": "{{appsmith.theme.borderRadius.appBorderRadius}}",
  "bottomRow": 113,
  "boxShadow": "none",
  "canEscapeKeyClose": true,
  "canOutsideClickClose": true,
  "children": [
    {
      "accentColor": "{{appsmith.theme.colors.primaryColor}}",
      "borderRadius": "{{appsmith.theme.borderRadius.appBorderRadius}}",
      "bottomRow": 220,
      "boxShadow": "none",
      "canExtend": true,
      "detachFromLayout": true,
      "displayName": "Canvas",
      "dynamicBindingPathList": [
        {
          "key": "borderRadius"
        },
        {
          "key": "accentColor"
        }
      ],
      "hideCard": true,
      "isDeprecated": false,
      "isDisabled": false,
      "isLoading": false,
      "isVisible": true,
      "key": "8tt50j9lv3",
      "leftColumn": 0,
      "minHeight": 100,
      "parentColumnSpace": 1,
      "parentId": "5tr0vabfvk",
      "parentRowSpace": 1,
      "renderMode": "CANVAS",
      "rightColumn": 480.75,
      "shouldScrollContents": false,
      "topRow": 0,
      "type": "CANVAS_WIDGET",
      "version": 1,
      "widgetId": "geemc5sx3q",
      "widgetName": "Canvas40"
    }
  ],
  "detachFromLayout": true,
  "displayName": "Modal",
  "dynamicBindingPathList": [
    {
      "key": "borderRadius"
    }
  ],
  "height": 100,
  "hideCard": false,
  "iconSVG": "/static/media/icon.4975978e.svg",
  "isCanvas": true,
  "isDeprecated": false,
  "isLoading": false,
  "key": "230m46svtj",
  "leftColumn": 18,
  "parentColumnSpace": 20.03125,
  "parentId": "0",
  "parentRowSpace": 10,
  "renderMode": "CANVAS",
  "rightColumn": 42,
  "shouldScrollContents": true,
  "topRow": 89,
  "type": "MODAL_WIDGET",
  "version": 2,
  "widgetId": "5tr0vabfvk",
  "widgetName": "Modal1",
  "width": 146
}